bids_path/__init__.py
bids_path/main.py
bids_path/py.typed
bids_path/resources/__init__.py
bids_path/resources/bids_tags.json
bids_path-0.0.1.dist-info/LICENSE
bids_path-0.0.1.dist-info/METADATA
bids_path-0.0.1.dist-info/WHEEL
bids_path-0.0.1.dist-info/entry_points.txt
bids_path-0.0.1.dist-info/RECORD
