Metadata-Version: 2.1
Name: bids-path
Version: 0.0.1
Summary: BIDS integration into snakemake workflows
Home-page: https://github.com/snakebids/bids_path
License: MIT
Author: Ali Khan
Author-email: alik@robarts.ca
Requires-Python: >=3.8,<3.12
Classifier: License :: OSI Approved :: MIT License
Classifier: Programming Language :: Python :: 3
Classifier: Programming Language :: Python :: 3.8
Classifier: Programming Language :: Python :: 3.9
Classifier: Programming Language :: Python :: 3.10
Classifier: Programming Language :: Python :: 3.11
Requires-Dist: more-itertools (>=8,<10)
Requires-Dist: typing-extensions (>=3.10.0)
Project-URL: Documentation, https://snakebids.readthedocs.io/
Project-URL: Repository, https://github.com/snakebids/bids_path
